[
    {
        "nom": "Blastoise",
        "types": [
            "water"
        ],
        "pv": 79,
        "attaque": 83,
        "defense": 100,
        "vitesse": 78,
        "niveau": 1,
        "exp": 0,
        "capacites": [],
        "evolution": null,
        "est_joueur": true
    },
    {
        "nom": "Pikachu",
        "types": [
            "electric"
        ],
        "pv": 35,
        "attaque": 55,
        "defense": 40,
        "vitesse": 90,
        "niveau": 1,
        "exp": 0,
        "capacites": [],
        "evolution": null,
        "est_joueur": true
    },
    {
        "nom": "Mewtwo",
        "types": [
            "psychic"
        ],
        "pv": 106,
        "attaque": 110,
        "defense": 90,
        "vitesse": 130,
        "niveau": 1,
        "exp": 0,
        "capacites": [],
        "evolution": null,
        "est_joueur": true
    },
    {
        "nom": "Mankey",
        "types": [
            "fighting"
        ],
        "pv": 40,
        "attaque": 80,
        "defense": 35,
        "vitesse": 70,
        "niveau": 1,
        "exp": 0,
        "capacites": [],
        "evolution": null,
        "est_joueur": true
    },
    {
        "nom": "Pidgeot",
        "types": [
            "normal",
            "flying"
        ],
        "pv": 83,
        "attaque": 80,
        "defense": 75,
        "vitesse": 101,
        "niveau": 1,
        "exp": 0,
        "capacites": [],
        "evolution": null,
        "est_joueur": true
    }
]